koltrast/__init__.py
koltrast/interval.py
koltrast-2.0.8.dist-info/LICENSE
koltrast-2.0.8.dist-info/METADATA
koltrast-2.0.8.dist-info/WHEEL
koltrast-2.0.8.dist-info/top_level.txt
koltrast-2.0.8.dist-info/RECORD
