Metadata-Version: 2.1
Name: koltrast
Version: 2.0.8
Summary: Create intervals and helpers for data pipelines
Author-email: Erik Bremstedt <erik.bremstedt@gmail.com>
Project-URL: Homepage, https://github.com/ebremstedt/koltrast
Project-URL: Issues, https://github.com/ebremstedt/koltrast/issues
Classifier: Programming Language :: Python :: 3
Classifier: License :: OSI Approved :: MIT License
Classifier: Operating System :: OS Independent
Requires-Python: >=3.8
License-File: LICENSE
Requires-Dist: pendulum==3.0.0
Requires-Dist: croniter==5.0.1
